nnabla_ext/cuda/__init__.py
nnabla_ext/cuda/_version.py
nnabla_ext/cuda/incompatible_gpu_list.py
nnabla_ext/cuda/init.cpython-310-x86_64-linux-gnu.so
nnabla_ext/cuda/libnnabla_cuda-114_8.so
nnabla_ext/cuda/nvtx.cpython-310-x86_64-linux-gnu.so
nnabla_ext/cuda/doc/LICENSE
nnabla_ext/cuda/doc/NOTICE.md
nnabla_ext/cuda/doc/third_party/LICENSES.md
nnabla_ext/cuda/experimental/__init__.py
nnabla_ext/cuda/experimental/_dali_iterator.py
nnabla_ext/cuda/experimental/dali_iterator.py
nnabla_ext/cuda/utils/__init__.py
nnabla_ext/cuda/utils/inspection/__init__.py
nnabla_ext/cuda/utils/inspection/profile.py
nnabla_ext/cudnn/__init__.py
nnabla_ext/cudnn/_version.py
nnabla_ext/cudnn/init.cpython-310-x86_64-linux-gnu.so
nnabla_ext_cuda114-1.33.1.dist-info/METADATA
nnabla_ext_cuda114-1.33.1.dist-info/WHEEL
nnabla_ext_cuda114-1.33.1.dist-info/top_level.txt
nnabla_ext_cuda114-1.33.1.dist-info/RECORD
